odoo/addons/edi_storage/README.rst
odoo/addons/edi_storage/__init__.py
odoo/addons/edi_storage/__manifest__.py
odoo/addons/edi_storage/components/__init__.py
odoo/addons/edi_storage/components/base.py
odoo/addons/edi_storage/components/check.py
odoo/addons/edi_storage/components/listener.py
odoo/addons/edi_storage/components/receive.py
odoo/addons/edi_storage/components/send.py
odoo/addons/edi_storage/data/cron.xml
odoo/addons/edi_storage/data/job_channel_data.xml
odoo/addons/edi_storage/data/queue_job_function_data.xml
odoo/addons/edi_storage/demo/edi_backend_demo.xml
odoo/addons/edi_storage/i18n/edi_storage.pot
odoo/addons/edi_storage/models/__init__.py
odoo/addons/edi_storage/models/edi_backend.py
odoo/addons/edi_storage/models/edi_exchange_type.py
odoo/addons/edi_storage/readme/CONTRIBUTORS.rst
odoo/addons/edi_storage/readme/DESCRIPTION.rst
odoo/addons/edi_storage/readme/USAGE.rst
odoo/addons/edi_storage/security/ir_model_access.xml
odoo/addons/edi_storage/static/description/icon.png
odoo/addons/edi_storage/static/description/index.html
odoo/addons/edi_storage/tests/__init__.py
odoo/addons/edi_storage/tests/common.py
odoo/addons/edi_storage/tests/test_component_match.py
odoo/addons/edi_storage/tests/test_components_base.py
odoo/addons/edi_storage/tests/test_edi_backend_storage.py
odoo/addons/edi_storage/tests/test_edi_storage_listener.py
odoo/addons/edi_storage/views/edi_backend_views.xml
odoo13_addon_edi_storage-13.0.1.8.2.dist-info/METADATA
odoo13_addon_edi_storage-13.0.1.8.2.dist-info/WHEEL
odoo13_addon_edi_storage-13.0.1.8.2.dist-info/top_level.txt
odoo13_addon_edi_storage-13.0.1.8.2.dist-info/RECORD
