Metadata-Version: 2.1
Name: odoo13-addon-edi-storage
Version: 13.0.1.8.2
Summary: Base module to allow exchanging files via storage backend (eg: SFTP).
Home-page: https://github.com/OCA/edi
Author: ACSONE,Odoo Community Association (OCA)
Author-email: support@odoo-community.org
License: LGPL-3
Platform: UNKNOWN
Classifier: Programming Language :: Python
Classifier: Framework :: Odoo
Classifier: Framework :: Odoo :: 13.0
Classifier: License :: OSI Approved :: GNU Lesser General Public License v3 (LGPLv3)
Classifier: Development Status :: 4 - Beta
Requires-Python: >=3.5
Requires-Dist: odoo13-addon-component
Requires-Dist: odoo13-addon-edi
Requires-Dist: odoo13-addon-storage-backend
Requires-Dist: odoo (<13.1dev,>=13.0a)
